quackpanda/__init__.py
quackpanda/core.py
quackpanda-0.1.2.dist-info/LICENSE
quackpanda-0.1.2.dist-info/METADATA
quackpanda-0.1.2.dist-info/WHEEL
quackpanda-0.1.2.dist-info/RECORD
