Metadata-Version: 2.1
Name: quackpanda
Version: 0.1.2
Summary: QuackPanda: SQL Capability for Pandas using DuckDB
Author: Your Name
Author-email: you@example.com
Requires-Python: >=3.10,<3.13
Classifier: Programming Language :: Python :: 3
Classifier: Programming Language :: Python :: 3.10
Classifier: Programming Language :: Python :: 3.11
Requires-Dist: duckdb (>=0.8.1,<0.9.0)
Requires-Dist: pandas (==1.5.3)
Requires-Dist: pyarrow (>=13.0.0,<14.0.0)
